LICENSE
MANIFEST.in
README.md
setup.cfg
setup.py
shuup_api_permission/__init__.py
shuup_api_permission/api.py
shuup_api_permission/apps.py
shuup_api_permission/authentication.py
shuup_api_permission/middleware.py
shuup_api_permission/models.py
shuup_api_permission/permissions.py
shuup_api_permission/serializers.py
shuup_api_permission/settings.py
shuup_api_permission/utils.py
shuup_api_permission.egg-info/PKG-INFO
shuup_api_permission.egg-info/SOURCES.txt
shuup_api_permission.egg-info/dependency_links.txt
shuup_api_permission.egg-info/requires.txt
shuup_api_permission.egg-info/top_level.txt
shuup_api_permission/admin_module/__init__.py
shuup_api_permission/admin_module/form_parts.py
shuup_api_permission/admin_module/forms.py
shuup_api_permission/admin_module/views/__init__.py
shuup_api_permission/admin_module/views/edit.py
shuup_api_permission/admin_module/views/list.py
shuup_api_permission/migrations/0001_initial.py
shuup_api_permission/migrations/__init__.py
shuup_api_permission/templates/shuup_api_permission/api_access_edit.jinja
shuup_api_permission/templates/shuup_api_permission/api_access_form_part.jinja
shuup_api_permission/templates/shuup_api_permission/permission_groups_edit.jinja
shuup_api_permission/templates/shuup_api_permission/permission_groups_form_part.jinja
shuup_api_permission/templates/shuup_api_permission/permissions_form_part.jinja
shuup_api_permission_tests/__init__.py
shuup_api_permission_tests/settings.py
shuup_api_permission_tests/test_admin.py
shuup_api_permission_tests/test_api_access.py
shuup_api_permission_tests/test_api_authentication.py
shuup_api_permission_tests/test_api_permissions.py