Metadata-Version: 1.1
Name: shuup-api-permission
Version: 0.1.3
Summary: Shuup API Permission
Home-page: https://github.com/chessbr/shuup-api-permission
Author: Christian Hess
Author-email: christianhess.rlz@gmail.com
License: MIT
Platform: UNKNOWN
Classifier: Programming Language :: Python
Classifier: Programming Language :: Python :: 3.5
Classifier: Programming Language :: Python :: 2.7
